snap_jolokia/__init__.py
snap_jolokia/_version.py
snap_jolokia/plugin.py
snap_plugin_collector_jolokia-1.dist-info/DESCRIPTION.rst
snap_plugin_collector_jolokia-1.dist-info/METADATA
snap_plugin_collector_jolokia-1.dist-info/RECORD
snap_plugin_collector_jolokia-1.dist-info/WHEEL
snap_plugin_collector_jolokia-1.dist-info/entry_points.txt
snap_plugin_collector_jolokia-1.dist-info/metadata.json
snap_plugin_collector_jolokia-1.dist-info/top_level.txt
